pyiono/__init__.py
pyiono/__main__.py
pyiono/imports.py
pyiono/math.py
pyiono/time.py
pyiono/transform.py
pyiono/cli/GIMs_Helpers.py
pyiono/cli/GTMs.py
pyiono/cli/IPP.py
pyiono/cli/cli.py
pyiono/cli/download_madrigal.py
pyiono/cli/g_gnss.py
pyiono/cli/v_analysis.py
pyiono/cli/v_data.py
pyiono/cli/v_download.py
pyiono/cli/v_lsq.py
pyiono/cli/v_rps_results.py
pyiono/cli/v_vgos.py
pyiono/vgos/cli.py
pyiono/vgos/download_madrigal.py
pyiono/vgos/madrigalDownload.py
pyiono/vgos/v_download.py
pyiono/vgos/v_test.py
pyiono-0.1.0.dist-info/LICENSE
pyiono-0.1.0.dist-info/METADATA
pyiono-0.1.0.dist-info/WHEEL
pyiono-0.1.0.dist-info/entry_points.txt
pyiono-0.1.0.dist-info/top_level.txt
pyiono-0.1.0.dist-info/RECORD
