Metadata-Version: 2.1
Name: pyiono
Version: 0.1.0
Summary: Ionosphere-related processing based on the input from space-geodetic data
Author-email: Grzegorz Kłopotek <klpotek@ethz.ch>, Mudathir Awadaljeed <mudathir.awadaljeed@gmail.com>
License: Apache License
Project-URL: Homepage, https://gitlab.ethz.ch/space-geodesy-open/pyiono
Keywords: Ionosphere,GNSS,VLBI
Classifier: Development Status :: 3 - Alpha
Classifier: License :: OSI Approved :: Apache Software License
Classifier: Programming Language :: Python
Classifier: Programming Language :: Python :: 3
Requires-Python: >=3.9
License-File: LICENSE
Requires-Dist: astropy (>=5.3.1)
Requires-Dist: magnetic-field-calculator (>=1.0.2)
Requires-Dist: pyproj (>=3.6.0)
Requires-Dist: matplotlib (>=3.7.2)
Requires-Dist: scipy (>=1.11.1)
Requires-Dist: aacgmv2 (>=2.6.3)
Requires-Dist: unlzw3 (>=0.2.2)
Requires-Dist: numpy (>=1.19.2)
Requires-Dist: madrigalWeb (>=3.2.3)
Requires-Dist: netCDF4 (>=1.6.4)
Provides-Extra: dev
Requires-Dist: bumpver ; extra == 'dev'
Requires-Dist: pip-tools ; extra == 'dev'
Requires-Dist: pytest ; extra == 'dev'
Requires-Dist: tox ; extra == 'dev'
Requires-Dist: pytest-cov ; extra == 'dev'
Requires-Dist: pytest-asyncio ; extra == 'dev'
Requires-Dist: coverage ; extra == 'dev'
Requires-Dist: sphinx ; extra == 'dev'
Requires-Dist: sphinx-rtd-theme ; extra == 'dev'
Requires-Dist: sphinx-autoapi ; extra == 'dev'
Requires-Dist: m2r2 ; extra == 'dev'
